{
  "sign_id": "fall",
  "display_name": "Fall",
  "sign_type": "static",
  "active_hand": "left",
  "critical_features": [
    "palm_normal",
    "wrist_flexion_deg",
    "finger_curls"
  ],
  "reference_sequence": [
    {
      "palm_normal": [
        0.0,
        0.0,
        -1.0
      ],
      "finger_curls": {
        "thumb": [
          170.52229886387462,
          166.9930025590277
        ],
        "index": [
          176.26823149473208,
          156.66324422109886,
          119.3574294460319
        ],
        "middle": [
          175.20232923486725,
          95.6687423999144,
          138.3660361712889
        ],
        "ring": [
          163.13847913096484,
          100.61968026253973,
          119.35836396193858
        ],
        "pinky": [
          158.46448397839103,
          131.2706928098892,
          88.70640616680105
        ]
      },
      "wrist_flexion_deg": 1.9976278888668952,
      "confidence": 1.0,
      "timestamp_ms": 0,
      "active_hand": "left"
    },
    {
      "palm_normal": [
        0.0,
        0.0,
        -1.0
      ],
      "finger_curls": {
        "thumb": [
          170.54206358283378,
          169.57745444654705
        ],
        "index": [
          177.37631610537775,
          145.86467301349546,
          0.0
        ],
        "middle": [
          175.17931412718434,
          71.70562475787135,
          129.67266933242078
        ],
        "ring": [
          165.3947607560293,
          98.53071615748189,
          110.55558265883523
        ],
        "pinky": [
          161.37554646750857,
          98.00473011459711,
          110.55555712765634
        ]
      },
      "wrist_flexion_deg": 1.9668234350779943,
      "confidence": 1.0,
      "timestamp_ms": 40,
      "active_hand": "left"
    },
    {
      "palm_normal": [
        0.0,
        0.0,
        -1.0
      ],
      "finger_curls": {
        "thumb": [
          170.52256848519337,
          166.99277495887338
        ],
        "index": [
          176.42078218545896,
          165.1126994271585,
          171.1985934788553
        ],
        "middle": [
          175.47043573315946,
          119.31754908085134,
          95.39653324452308
        ],
        "ring": [
          167.81596739496564,
          115.99216381420489,
          110.58247300699452
        ],
        "pinky": [
          164.30527151852303,
          145.20007988599002,
          99.50538579818566
        ]
      },
      "wrist_flexion_deg": 2.4372686036835653,
      "confidence": 1.0,
      "timestamp_ms": 80,
      "active_hand": "left"
    },
    {
      "palm_normal": [
        0.0,
        0.0,
        -1.0
      ],
      "finger_curls": {
        "thumb": [
          169.42228903519106,
          170.69713666480826
        ],
        "index": [
          177.02447785005523,
          145.51294076821782,
          139.84404641781916
        ],
        "middle": [
          174.33109177088969,
          119.63165855649677,
          95.39467488296974
        ],
        "ring": [
          166.64680848949706,
          115.99204603325276,
          99.78425400682127
        ],
        "pinky": [
          159.3148397170906,
          147.84878772958695,
          99.50524729276188
        ]
      },
      "wrist_flexion_deg": 1.5994881508683432,
      "confidence": 1.0,
      "timestamp_ms": 120,
      "active_hand": "left"
    },
    {
      "palm_normal": [
        0.0,
        0.0,
        -1.0
      ],
      "finger_curls": {
        "thumb": [
          168.34558111655693,
          166.99268391990753
        ],
        "index": [
          175.86203668240427,
          155.99743531337785,
          160.99223525823425
        ],
        "middle": [
          175.77241996833055,
          114.64838944219757,
          118.79331875626123
        ],
        "ring": [
          168.06351004398928,
          115.59381269925186,
          129.77693074093523
        ],
        "pinky": [
          159.65632721682238,
          151.13437955125184,
          96.21979213864981
        ]
      },
      "wrist_flexion_deg": 2.9337821859540645,
      "confidence": 1.0,
      "timestamp_ms": 160,
      "active_hand": "left"
    },
    {
      "palm_normal": [
        0.0,
        0.0,
        -1.0
      ],
      "finger_curls": {
        "thumb": [
          164.2040502951004,
          168.59982315902604
        ],
        "index": [
          173.8239373145085,
          160.7029406262915,
          143.52431485706714
        ],
        "middle": [
          175.5151973099861,
          148.48679170104697,
          102.90725092423484
        ],
        "ring": [
          167.73739793297062,
          131.43781729813617,
          144.58287689216323
        ],
        "pinky": [
          162.91611812715476,
          136.57978821402088,
          169.01613260209928
        ]
      },
      "wrist_flexion_deg": 2.927235858093852,
      "confidence": 1.0,
      "timestamp_ms": 200,
      "active_hand": "left"
    },
    {
      "palm_normal": [
        0.0,
        0.0,
        -1.0
      ],
      "finger_curls": {
        "thumb": [
          169.74241545992007,
          167.2535783365383
        ],
        "index": [
          176.47518808386272,
          155.99782150859858,
          160.99267565494094
        ],
        "middle": [
          172.87489362726606,
          116.69833181206018,
          129.7764241716658
        ],
        "ring": [
          163.0961568979701,
          135.38643288823008,
          113.93263307558595
        ],
        "pinky": [
          157.8982211896887,
          150.4641193326889,
          130.15565539022796
        ]
      },
      "wrist_flexion_deg": 2.284476397847024,
      "confidence": 1.0,
      "timestamp_ms": 240,
      "active_hand": "left"
    },
    {
      "palm_normal": [
        0.0,
        0.0,
        -1.0
      ],
      "finger_curls": {
        "thumb": [
          168.345293722796,
          166.99268391990753
        ],
        "index": [
          177.02460943221303,
          156.31105525120162,
          119.35782715301129
        ],
        "middle": [
          172.8750588273315,
          116.69787118387669,
          118.79364414755602
        ],
        "ring": [
          164.5347430196907,
          133.9477216184345,
          120.62034892983313
        ],
        "pinky": [
          160.19446692215053,
          151.13481107725556,
          126.86977128744887
        ]
      },
      "wrist_flexion_deg": 2.070937400271317,
      "confidence": 1.0,
      "timestamp_ms": 280,
      "active_hand": "left"
    },
    {
      "palm_normal": [
        0.0,
        0.0,
        -1.0
      ],
      "finger_curls": {
        "thumb": [
          169.73570534074145,
          167.32525568327165
        ],
        "index": [
          176.71145219052997,
          155.99818252246115,
          160.9903060170462
        ],
        "middle": [
          174.64415784928408,
          130.77252860058326,
          113.93343638969807
        ],
        "ring": [
          164.71562701946144,
          145.3781647470678,
          109.19002212018522
        ],
        "pinky": [
          160.5133052933677,
          151.13495963675223,
          126.86979690062019
        ]
      },
      "wrist_flexion_deg": 2.056332212392541,
      "confidence": 1.0,
      "timestamp_ms": 320,
      "active_hand": "left"
    },
    {
      "palm_normal": [
        0.0,
        0.0,
        -1.0
      ],
      "finger_curls": {
        "thumb": [
          168.34575017497522,
          166.53842305731808
        ],
        "index": [
          176.4207274817935,
          156.31129325513734,
          160.98962453669503
        ],
        "middle": [
          173.7013805366598,
          143.9721564629219,
          109.19137451868605
        ],
        "ring": [
          166.07959919816477,
          144.85182279149848,
          133.1527780366144
        ],
        "pinky": [
          161.12207471200196,
          150.52556306140855,
          150.8320961194853
        ]
      },
      "wrist_flexion_deg": 2.680514391328435,
      "confidence": 1.0,
      "timestamp_ms": 360,
      "active_hand": "left"
    },
    {
      "palm_normal": [
        0.0,
        0.0,
        -1.0
      ],
      "finger_curls": {
        "thumb": [
          170.5227758913797,
          166.53834970713024
        ],
        "index": [
          176.65525613862994,
          162.20227375501364,
          154.5040041092259
        ],
        "middle": [
          174.64415784928408,
          142.2039489348858,
          109.18950864558954
        ],
        "ring": [
          164.88708108983434,
          145.37868769228243,
          133.15224906226226
        ],
        "pinky": [
          163.57212132235074,
          141.7932695776199,
          163.80342059768026
        ]
      },
      "wrist_flexion_deg": 1.6343449817544236,
      "confidence": 1.0,
      "timestamp_ms": 400,
      "active_hand": "left"
    },
    {
      "palm_normal": [
        0.0,
        0.0,
        -1.0
      ],
      "finger_curls": {
        "thumb": [
          166.2839827305851,
          171.31144403014264
        ],
        "index": [
          176.71145219052997,
          162.48199364008883,
          154.508010979171
        ],
        "middle": [
          172.8750588273315,
          132.5416797900635,
          144.58324225501133
        ],
        "ring": [
          164.71556224407374,
          140.1642110849845,
          114.40493795468375
        ],
        "pinky": [
          160.51334624326466,
          151.1351718658168,
          150.83289494825343
        ]
      },
      "wrist_flexion_deg": 1.6110693980617707,
      "confidence": 1.0,
      "timestamp_ms": 440,
      "active_hand": "left"
    },
    {
      "palm_normal": [
        0.0,
        0.0,
        -1.0
      ],
      "finger_curls": {
        "thumb": [
          167.25783558857438,
          165.14178463857567
        ],
        "index": [
          176.19481144291208,
          169.36649264836873,
          147.3424466716248
        ],
        "middle": [
          172.87489362726606,
          152.01340604700428,
          149.0741723687739
        ],
        "ring": [
          165.06082730042573,
          152.89283019289567,
          125.11196273056842
        ],
        "pinky": [
          160.8029561614195,
          150.52572963990116,
          150.83285290413656
        ]
      },
      "wrist_flexion_deg": 1.6110693980617707,
      "confidence": 1.0,
      "timestamp_ms": 480,
      "active_hand": "left"
    },
    {
      "palm_normal": [
        0.0,
        0.0,
        -1.0
      ],
      "finger_curls": {
        "thumb": [
          165.8610493912219,
          166.1404727786552
        ],
        "index": [
          175.58172524494964,
          155.71786001187922,
          150.0075122799453
        ],
        "middle": [
          175.47052222109838,
          136.9894902061588,
          107.71636771462202
        ],
        "ring": [
          166.07947143807337,
          144.8524634683003,
          109.19010167273066
        ],
        "pinky": [
          161.1219797174038,
          158.03828625111777,
          119.3577076448395
        ]
      },
      "wrist_flexion_deg": 2.2273015131917986,
      "confidence": 1.0,
      "timestamp_ms": 520,
      "active_hand": "left"
    },
    {
      "palm_normal": [
        0.0,
        0.0,
        -1.0
      ],
      "finger_curls": {
        "thumb": [
          165.8610493912219,
          166.53848173775083
        ],
        "index": [
          175.58194690326715,
          166.42602664115222,
          139.30059433202385
        ],
        "middle": [
          173.24645602006615,
          143.60123102827075,
          133.15233800453225
        ],
        "ring": [
          165.24182537836091,
          144.85218465399714,
          133.15241758456776
        ],
        "pinky": [
          160.26481815084873,
          152.28455291075173,
          155.76152916936582
        ]
      },
      "wrist_flexion_deg": 1.1347043729841115,
      "confidence": 1.0,
      "timestamp_ms": 560,
      "active_hand": "left"
    },
    {
      "palm_normal": [
        0.0,
        0.0,
        -1.0
      ],
      "finger_curls": {
        "thumb": [
          164.63038126492768,
          168.22332570273775
        ],
        "index": [
          173.72583237782214,
          160.34576505119034,
          112.87377698626686
        ],
        "middle": [
          175.47047897692292,
          142.20313536364426,
          102.50166626913438
        ],
        "ring": [
          166.5447473185674,
          139.17303574964794,
          118.79335382832801
        ],
        "pinky": [
          161.64499851735627,
          150.00312659323117,
          157.5198869272366
        ]
      },
      "wrist_flexion_deg": 2.187938211623336,
      "confidence": 1.0,
      "timestamp_ms": 600,
      "active_hand": "left"
    },
    {
      "palm_normal": [
        0.0,
        0.0,
        -1.0
      ],
      "finger_curls": {
        "thumb": [
          163.7995766176155,
          168.59996138056573
        ],
        "index": [
          173.63612986200977,
          164.73893764986965,
          108.64958962864593
        ],
        "middle": [
          174.11753395891037,
          138.3872291253204,
          96.73362303444038
        ],
        "ring": [
          166.38611301286883,
          132.95671542234066,
          113.93160371992542
        ],
        "pinky": [
          161.12188472326622,
          150.52579904785932,
          157.52044069023717
        ]
      },
      "wrist_flexion_deg": 2.2325676742926635,
      "confidence": 1.0,
      "timestamp_ms": 640,
      "active_hand": "left"
    },
    {
      "palm_normal": [
        0.0,
        0.0,
        -1.0
      ],
      "finger_curls": {
        "thumb": [
          161.64279713318365,
          166.20296996878076
        ],
        "index": [
          172.90543782047288,
          164.57045132829424,
          139.30003919747563
        ],
        "middle": [
          173.24645602006615,
          157.3955284311422,
          119.35799955848977
        ],
        "ring": [
          165.3354632573171,
          150.66940355862022,
          126.87011279710583
        ],
        "pinky": [
          162.3649338779115,
          155.23647729165887,
          169.20221680354877
        ]
      },
      "wrist_flexion_deg": 1.159102893062624,
      "confidence": 1.0,
      "timestamp_ms": 680,
      "active_hand": "left"
    },
    {
      "palm_normal": [
        0.0,
        0.0,
        -1.0
      ],
      "finger_curls": {
        "thumb": [
          160.78618985780093,
          164.40888656774172
        ],
        "index": [
          173.59399688466294,
          155.46597119568116,
          150.00642605101487
        ],
        "middle": [
          175.0363917102516,
          149.88338014946663,
          126.87015975480307
        ],
        "ring": [
          166.21868786350046,
          144.38748783247573,
          133.1519447870543
        ],
        "pinky": [
          160.80288345972966,
          158.03825885637102,
          179.97202354488172
        ]
      },
      "wrist_flexion_deg": 2.9245596801493803,
      "confidence": 1.0,
      "timestamp_ms": 720,
      "active_hand": "left"
    },
    {
      "palm_normal": [
        0.0,
        0.0,
        -1.0
      ],
      "finger_curls": {
        "thumb": [
          160.42876649978518,
          165.37260651681447
        ],
        "index": [
          173.41468075723986,
          155.2358984325642,
          150.00890598441475
        ],
        "middle": [
          174.89880538419007,
          149.88328486268335,
          126.87023659473351
        ],
        "ring": [
          164.84089886181053,
          152.5241848092892,
          126.86980970720909
        ],
        "pinky": [
          161.7114854973024,
          158.0377474937266,
          169.20281837946823
        ]
      },
      "wrist_flexion_deg": 2.811532994956668,
      "confidence": 1.0,
      "timestamp_ms": 760,
      "active_hand": "left"
    },
    {
      "palm_normal": [
        0.0,
        0.0,
        -1.0
      ],
      "finger_curls": {
        "thumb": [
          157.48833486614302,
          168.58059193058594
        ],
        "index": [
          173.97461372348943,
          168.88555252306205,
          147.34263020556816
        ],
        "middle": [
          175.7726979352878,
          160.8476763675474,
          133.80117094079654
        ],
        "ring": [
          165.24158406866897,
          163.77720366522496,
          138.18957505428753
        ],
        "pinky": [
          162.71485331837934,
          155.588614957384,
          169.2010502052428
        ]
      },
      "wrist_flexion_deg": 2.015574025138041,
      "confidence": 1.0,
      "timestamp_ms": 800,
      "active_hand": "left"
    },
    {
      "palm_normal": [
        0.0,
        0.0,
        -1.0
      ],
      "finger_curls": {
        "thumb": [
          157.60545384353654,
          169.32148432949313
        ],
        "index": [
          174.28015211641346,
          160.3671597223642,
          164.070499315759
        ],
        "middle": [
          177.5066003635935,
          148.2765475804016,
          149.07529540630225
        ],
        "ring": [
          167.20603856044667,
          142.51681411663873,
          133.15212267083808
        ],
        "pinky": [
          162.36517060573325,
          147.72424727247252,
          157.52136067994428
        ]
      },
      "wrist_flexion_deg": 2.2760647765471433,
      "confidence": 1.0,
      "timestamp_ms": 840,
      "active_hand": "left"
    },
    {
      "palm_normal": [
        0.0,
        0.0,
        -1.0
      ],
      "finger_curls": {
        "thumb": [
          164.17390590132536,
          168.31333518068251
        ],
        "index": [
          176.81813802392372,
          160.59520665817487,
          174.8699268973193
        ],
        "middle": [
          176.78052091448856,
          149.2002752790861,
          165.65224949024537
        ],
        "ring": [
          166.63956480756147,
          145.199720852713,
          154.11818247369843
        ],
        "pinky": [
          161.7737840796709,
          154.93125207384116,
          143.3199413918183
        ]
      },
      "wrist_flexion_deg": 1.610947923673727,
      "confidence": 1.0,
      "timestamp_ms": 880,
      "active_hand": "left"
    },
    {
      "palm_normal": [
        0.0,
        0.0,
        -1.0
      ],
      "finger_curls": {
        "thumb": [
          163.4693680388776,
          169.4624931388342
        ],
        "index": [
          174.7991836519338,
          162.6631032914017,
          160.4012179420337
        ],
        "middle": [
          175.1769983335669,
          155.4651981028019,
          150.0087215201564
        ],
        "ring": [
          165.2866418182863,
          146.96836512966016,
          130.15656692784765
        ],
        "pinky": [
          160.28079374293208,
          150.00287385330887,
          150.83195597614483
        ]
      },
      "wrist_flexion_deg": 2.071031902719645,
      "confidence": 1.0,
      "timestamp_ms": 920,
      "active_hand": "left"
    },
    {
      "palm_normal": [
        0.0,
        0.0,
        -1.0
      ],
      "finger_curls": {
        "thumb": [
          158.4640746298486,
          168.46291457892002
        ],
        "index": [
          172.15067023498656,
          162.51049360756062,
          180.0
        ],
        "middle": [
          177.80456057222085,
          147.95424010077318,
          160.5289746684504
        ],
        "ring": [
          167.7098847243376,
          150.24324890522448,
          125.11248457985927
        ],
        "pinky": [
          162.21528366393014,
          155.23628161956057,
          143.32061029921672
        ]
      },
      "wrist_flexion_deg": 2.698998803210715,
      "confidence": 1.0,
      "timestamp_ms": 960,
      "active_hand": "left"
    },
    {
      "palm_normal": [
        0.0,
        0.0,
        -1.0
      ],
      "finger_curls": {
        "thumb": [
          161.3815678080232,
          168.4628804283931
        ],
        "index": [
          173.31413785497966,
          165.24785937501795,
          174.9448338443071
        ],
        "middle": [
          173.88457830405198,
          161.0005939867852,
          150.53133828262762
        ],
        "ring": [
          166.1215239999296,
          146.9688036861578,
          154.1184719454968
        ],
        "pinky": [
          158.0237077048623,
          159.77222506398107,
          143.3205874304146
        ]
      },
      "wrist_flexion_deg": 1.8150989420765347,
      "confidence": 1.0,
      "timestamp_ms": 1000,
      "active_hand": "left"
    },
    {
      "palm_normal": [
        0.0,
        0.0,
        -1.0
      ],
      "finger_curls": {
        "thumb": [
          157.46377382630112,
          167.7693560721145
        ],
        "index": [
          171.26542401350954,
          165.24732292204123,
          174.86145505761056
        ],
        "middle": [
          174.75540099573539,
          161.0009191782723,
          170.0025296419333
        ],
        "ring": [
          164.64554128379072,
          159.0624266264911,
          138.93041688718088
        ],
        "pinky": [
          161.24211491547976,
          157.0611122178591,
          160.99109236976471
        ]
      },
      "wrist_flexion_deg": 2.6860584866689314,
      "confidence": 1.0,
      "timestamp_ms": 1040,
      "active_hand": "left"
    },
    {
      "palm_normal": [
        0.0,
        0.0,
        -1.0
      ],
      "finger_curls": {
        "thumb": [
          160.7038190508085,
          164.13093570947694
        ],
        "index": [
          171.73753632171534,
          165.40063978357227,
          174.86156944907927
        ],
        "middle": [
          176.0251675024336,
          159.08220837905492,
          162.58784041678035
        ],
        "ring": [
          166.12138162397903,
          157.76733265263613,
          138.93073917724323
        ],
        "pinky": [
          163.06665458395167,
          155.23640391445227,
          172.48824602422866
        ]
      },
      "wrist_flexion_deg": 2.4823853013728683,
      "confidence": 1.0,
      "timestamp_ms": 1080,
      "active_hand": "left"
    },
    {
      "palm_normal": [
        0.0,
        0.0,
        -1.0
      ],
      "finger_curls": {
        "thumb": [
          158.6946138857934,
          166.14008785163273
        ],
        "index": [
          172.5997536137577,
          162.66308037052235,
          175.1520015106286
        ],
        "middle": [
          174.42933189378923,
          161.30406485058387,
          168.2447459809295
        ],
        "ring": [
          165.87863368367942,
          147.38307434990375,
          165.57406998549206
        ],
        "pinky": [
          160.5884236595584,
          158.0383866988005,
          160.99086170305378
        ]
      },
      "wrist_flexion_deg": 2.702260425607818,
      "confidence": 1.0,
      "timestamp_ms": 1120,
      "active_hand": "left"
    },
    {
      "palm_normal": [
        0.0,
        0.0,
        -1.0
      ],
      "finger_curls": {
        "thumb": [
          161.38162129193088,
          168.86098957335426
        ],
        "index": [
          173.72570738264912,
          162.6633783442453,
          171.1981471019475
        ],
        "middle": [
          176.0033527785413,
          149.71091563483174,
          160.52922055912356
        ],
        "ring": [
          165.87873166740516,
          147.3832327440409,
          130.15611562583013
        ],
        "pinky": [
          159.7578486627665,
          144.2440675086862,
          163.80258806808405
        ]
      },
      "wrist_flexion_deg": 2.4489653636267366,
      "confidence": 1.0,
      "timestamp_ms": 1160,
      "active_hand": "left"
    },
    {
      "palm_normal": [
        0.0,
        0.0,
        -1.0
      ],
      "finger_curls": {
        "thumb": [
          168.26885839213932,
          170.31216863999677
        ],
        "index": [
          175.99263647488306,
          159.16100594955608,
          164.07114637571794
        ],
        "middle": [
          172.06934278774634,
          146.96882874668503,
          165.57327493243278
        ],
        "ring": [
          162.63413182278023,
          141.60347813017012,
          138.36628804931706
        ],
        "pinky": [
          157.33469060675543,
          141.45275141255297,
          138.36649366495743
        ]
      },
      "wrist_flexion_deg": 1.117326001408149,
      "confidence": 1.0,
      "timestamp_ms": 1200,
      "active_hand": "left"
    },
    {
      "palm_normal": [
        0.0,
        0.0,
        -1.0
      ],
      "finger_curls": {
        "thumb": [
          167.38663246169105,
          169.46273590427214
        ],
        "index": [
          175.0292132800895,
          152.25361066363843,
          150.0081066467267
        ],
        "middle": [
          173.27223461860785,
          136.7088905254476,
          138.3665656306277
        ],
        "ring": [
          163.57495933992615,
          128.65539230739267,
          125.3873719249482
        ],
        "pinky": [
          157.95903213332426,
          139.6383240824162,
          114.40341164044055
        ]
      },
      "wrist_flexion_deg": 0.9339798892165465,
      "confidence": 1.0,
      "timestamp_ms": 1240,
      "active_hand": "left"
    },
    {
      "palm_normal": [
        0.0,
        0.0,
        -1.0
      ],
      "finger_curls": {
        "thumb": [
          171.86496117419824,
          168.31326774199226
        ],
        "index": [
          175.19221349375576,
          152.25278910163098,
          160.99209894695935
        ],
        "middle": [
          173.3526744242619,
          136.7100559541296,
          107.71400692837987
        ],
        "ring": [
          166.12393037011685,
          115.24229791517288,
          110.5832992708102
        ],
        "pinky": [
          160.17839698958113,
          118.90795253961507,
          125.38846106895394
        ]
      },
      "wrist_flexion_deg": 1.439534532033425,
      "confidence": 1.0,
      "timestamp_ms": 1280,
      "active_hand": "left"
    },
    {
      "palm_normal": [
        0.0,
        0.0,
        -1.0
      ],
      "finger_curls": {
        "thumb": [
          164.4675578591083,
          166.17463045226748
        ],
        "index": [
          170.87723222290168,
          170.46108415817827,
          167.44800590348885
        ],
        "middle": [
          176.65203830734796,
          133.32959057445538,
          169.01606090657452
        ],
        "ring": [
          169.34199826353924,
          127.43092971922152,
          113.9333280354099
        ],
        "pinky": [
          165.17343440098227,
          131.63335827309405,
          107.71674236009436
        ]
      },
      "wrist_flexion_deg": 1.6616571142130492,
      "confidence": 1.0,
      "timestamp_ms": 1320,
      "active_hand": "left"
    },
    {
      "palm_normal": [
        0.0,
        0.0,
        -1.0
      ],
      "finger_curls": {
        "thumb": [
          164.46754510594272,
          168.322139224941
        ],
        "index": [
          169.48417709779713,
          154.19906237049392,
          154.50755075433543
        ],
        "middle": [
          176.73655184226874,
          133.24498788053063,
          114.40327663564611
        ],
        "ring": [
          169.46075659349003,
          111.4674619500678,
          110.58337952625368
        ],
        "pinky": [
          164.7189050039895,
          131.63386089034051,
          107.71699152665522
        ]
      },
      "wrist_flexion_deg": 1.8464199417881615,
      "confidence": 1.0,
      "timestamp_ms": 1360,
      "active_hand": "left"
    },
    {
      "palm_normal": [
        0.0,
        0.0,
        -1.0
      ],
      "finger_curls": {
        "thumb": [
          165.46868805015652,
          165.1735011298237
        ],
        "index": [
          171.20301382269844,
          158.04295296372135,
          141.20630423112812
        ],
        "middle": [
          174.4558505835563,
          134.70022167276537,
          96.73258924163424
        ],
        "ring": [
          166.7297352371923,
          129.4388143414373,
          102.95051124930147
        ],
        "pinky": [
          164.71893091964523,
          131.63371010475504,
          107.71516132566704
        ]
      },
      "wrist_flexion_deg": 0.812047193556674,
      "confidence": 1.0,
      "timestamp_ms": 1400,
      "active_hand": "left"
    },
    {
      "palm_normal": [
        0.0,
        0.0,
        -1.0
      ],
      "finger_curls": {
        "thumb": [
          164.35154392699107,
          164.29131479960662
        ],
        "index": [
          168.5554186975855,
          166.58031141834454,
          174.91076441001985
        ],
        "middle": [
          178.30441724043237,
          143.13022302100075,
          150.83296502190439
        ],
        "ring": [
          171.1193341943261,
          125.41706055276522,
          113.93272274761107
        ],
        "pinky": [
          165.987427946594,
          129.4857914002364,
          138.36667357932376
        ]
      },
      "wrist_flexion_deg": 1.5940957032154568,
      "confidence": 1.0,
      "timestamp_ms": 1440,
      "active_hand": "left"
    },
    {
      "palm_normal": [
        0.0,
        0.0,
        -1.0
      ],
      "finger_curls": {
        "thumb": [
          165.35062008609813,
          162.99061765543448
        ],
        "index": [
          164.91229022515563,
          166.15584991929904,
          98.00470080067622
        ],
        "middle": [
          175.40577153390163,
          138.53587937453634,
          77.02669270328455
        ],
        "ring": [
          175.57158516094168,
          128.0565063499141,
          96.73337071141927
        ],
        "pinky": [
          165.98748436312533,
          137.69676449406455,
          130.15565539022796
        ]
      },
      "wrist_flexion_deg": 3.100467402466738,
      "confidence": 1.0,
      "timestamp_ms": 1480,
      "active_hand": "left"
    },
    {
      "palm_normal": [
        0.0,
        0.0,
        -1.0
      ],
      "finger_curls": {
        "thumb": [
          166.35108896168117,
          161.9903479076188
        ],
        "index": [
          165.06689581734724,
          175.40577153390163,
          150.64323530050137
        ],
        "middle": [
          174.51048460980243,
          146.04764448970425,
          77.72473721172668
        ],
        "ring": [
          175.62337019168586,
          136.4561528257084,
          69.51314825117548
        ],
        "pinky": [
          166.34219123641412,
          135.82273331247808,
          130.1553694201629
        ]
      },
      "wrist_flexion_deg": 3.675409635465676,
      "confidence": 1.0,
      "timestamp_ms": 1520,
      "active_hand": "left"
    },
    {
      "palm_normal": [
        0.0,
        0.0,
        -1.0
      ],
      "finger_curls": {
        "thumb": [
          165.24065908392024,
          165.17184634119045
        ],
        "index": [
          162.99192523785834,
          167.46557075000374,
          173.58106245168267
        ],
        "middle": [
          172.18867143507876,
          133.7292165218582,
          69.51272170669417
        ],
        "ring": [
          176.451272654319,
          117.07342431543509,
          79.90631998575725
        ],
        "pinky": [
          167.38456828487085,
          116.62865857637209,
          107.71623148009884
        ]
      },
      "wrist_flexion_deg": 4.013125762681534,
      "confidence": 1.0,
      "timestamp_ms": 1560,
      "active_hand": "left"
    },
    {
      "palm_normal": [
        0.0,
        0.0,
        -1.0
      ],
      "finger_curls": {
        "thumb": [
          176.01365569867443,
          161.07158141321378
        ],
        "index": [
          170.7180959977195,
          177.5222711098354,
          180.0
        ],
        "middle": [
          178.8594472906508,
          87.85240051046591,
          105.70880092970027
        ],
        "ring": [
          174.42437363693764,
          87.31620683595925,
          119.35747450635058
        ],
        "pinky": [
          167.51086039356557,
          86.78048758722616,
          119.35764299293616
        ]
      },
      "wrist_flexion_deg": 1.0428646600437745,
      "confidence": 1.0,
      "timestamp_ms": 1600,
      "active_hand": "left"
    },
    {
      "palm_normal": [
        0.0,
        0.0,
        -1.0
      ],
      "finger_curls": {
        "thumb": [
          174.21629304551286,
          164.29151661895128
        ],
        "index": [
          167.45127487449162,
          175.71069977522717,
          169.38056746070285
        ],
        "middle": [
          175.71069977522717,
          146.35250781983035,
          58.715459748565166
        ],
        "ring": [
          177.21399542530986,
          115.7041647961809,
          79.90589245801708
        ],
        "pinky": [
          166.95916344869823,
          128.4139569529954,
          68.92210499784828
        ]
      },
      "wrist_flexion_deg": 1.46473488182189,
      "confidence": 1.0,
      "timestamp_ms": 1640,
      "active_hand": "left"
    },
    {
      "palm_normal": [
        0.0,
        0.0,
        -1.0
      ],
      "finger_curls": {
        "thumb": [
          167.49129338233863,
          165.65784576450662
        ],
        "index": [
          165.35840015742932,
          167.97290183557035,
          171.99484152719495
        ],
        "middle": [
          176.91263038457845,
          148.63081379791637,
          119.3558288380763
        ],
        "ring": [
          177.41600735717847,
          85.71086076814323,
          119.35755091302347
        ],
        "pinky": [
          169.6470789178562,
          126.27751934219008,
          77.72424004762846
        ]
      },
      "wrist_flexion_deg": 2.552056264854114,
      "confidence": 1.0,
      "timestamp_ms": 1680,
      "active_hand": "left"
    },
    {
      "palm_normal": [
        0.0,
        0.0,
        -1.0
      ],
      "finger_curls": {
        "thumb": [
          168.8576313702439,
          164.29142832267698
        ],
        "index": [
          166.4510039108886,
          173.89035129172694,
          158.64559441926164
        ],
        "middle": [
          175.95745936012742,
          148.74702384381467,
          58.716670570298845
        ],
        "ring": [
          176.27763560233944,
          129.62154418511832,
          96.73151289587148
        ],
        "pinky": [
          167.92406128842234,
          129.15570652481983,
          77.72354104555119
        ]
      },
      "wrist_flexion_deg": 3.548451467529068,
      "confidence": 1.0,
      "timestamp_ms": 1720,
      "active_hand": "left"
    },
    {
      "palm_normal": [
        0.0,
        0.0,
        -1.0
      ],
      "finger_curls": {
        "thumb": [
          171.48103430792213,
          161.36401170058363
        ],
        "index": [
          165.23687930053202,
          176.21389939163487,
          150.6416052788341
        ],
        "middle": [
          175.10266969771433,
          127.84648959128216,
          77.72516534877435
        ],
        "ring": [
          173.85062757371924,
          57.202184375276595,
          150.00797000973935
        ],
        "pinky": [
          166.62294847625543,
          87.07283664310461,
          119.35850698085268
        ]
      },
      "wrist_flexion_deg": 2.251771618503356,
      "confidence": 1.0,
      "timestamp_ms": 1760,
      "active_hand": "left"
    },
    {
      "palm_normal": [
        0.0,
        0.0,
        -1.0
      ],
      "finger_curls": {
        "thumb": [
          168.85809085480562,
          161.6074147618351
        ],
        "index": [
          167.23293115260685,
          178.20998059209822,
          180.0
        ],
        "middle": [
          177.0990295689476,
          148.85223248570097,
          179.98021765897056
        ],
        "ring": [
          171.99520937695823,
          139.84356979951994,
          88.52351254534888
        ],
        "pinky": [
          164.29131479960662,
          131.63380148991627,
          88.52211658840442
        ]
      },
      "wrist_flexion_deg": 2.5244494961494763,
      "confidence": 1.0,
      "timestamp_ms": 1800,
      "active_hand": "left"
    },
    {
      "palm_normal": [
        0.0,
        0.0,
        -1.0
      ],
      "finger_curls": {
        "thumb": [
          168.85741930675604,
          164.2915040051682
        ],
        "index": [
          166.69876561478807,
          175.5949999830975,
          173.58149012634337
        ],
        "middle": [
          174.06610906544216,
          160.50464624796948,
          180.0
        ],
        "ring": [
          177.1489202091912,
          135.82183652000467,
          171.78948053620954
        ],
        "pinky": [
          166.97524633143848,
          147.95838533814026,
          119.35781539810293
        ]
      },
      "wrist_flexion_deg": 3.8583869427271096,
      "confidence": 1.0,
      "timestamp_ms": 1840,
      "active_hand": "left"
    },
    {
      "palm_normal": [
        0.0,
        0.0,
        -1.0
      ],
      "finger_curls": {
        "thumb": [
          167.69933241968445,
          160.2591452008468
        ],
        "index": [
          164.98505443548245,
          177.36745311650708,
          178.4132871606063
        ],
        "middle": [
          177.3277500525232,
          178.30418642214482,
          180.0
        ],
        "ring": [
          173.75395685670054,
          129.620648601099,
          138.36594878532526
        ],
        "pinky": [
          165.9142316163179,
          128.94922708211791,
          64.07603631324076
        ]
      },
      "wrist_flexion_deg": 2.600980537926017,
      "confidence": 1.0,
      "timestamp_ms": 1880,
      "active_hand": "left"
    },
    {
      "palm_normal": [
        0.0,
        0.0,
        -1.0
      ],
      "finger_curls": {
        "thumb": [
          167.49283871108676,
          160.67171436732713
        ],
        "index": [
          165.29808882987572,
          178.43015015833345,
          174.6441212621173
        ],
        "middle": [
          178.21008992516727,
          178.2101992649129,
          180.0
        ],
        "ring": [
          175.3002203889733,
          155.4222451075528,
          175.1535777286182
        ],
        "pinky": [
          165.4423607096599,
          161.6071982932966,
          105.70900136901363
        ]
      },
      "wrist_flexion_deg": 1.818653509477002,
      "confidence": 1.0,
      "timestamp_ms": 1920,
      "active_hand": "left"
    },
    {
      "palm_normal": [
        0.0,
        0.0,
        -1.0
      ],
      "finger_curls": {
        "thumb": [
          162.09381368166072,
          166.7688607024098
        ],
        "index": [
          168.58418025341092,
          180.0,
          180.0
        ],
        "middle": [
          176.81346538270748,
          178.46557885577766,
          173.58121518937548
        ],
        "ring": [
          175.2754853165294,
          164.25310296215238,
          177.9392943617033
        ],
        "pinky": [
          166.18661163963822,
          165.42432836380988,
          163.32251318701987
        ]
      },
      "wrist_flexion_deg": 3.053257843901649,
      "confidence": 1.0,
      "timestamp_ms": 1960,
      "active_hand": "left"
    },
    {
      "palm_normal": [
        0.0,
        0.0,
        -1.0
      ],
      "finger_curls": {
        "thumb": [
          161.09355480038542,
          169.58096628627789
        ],
        "index": [
          167.48120605539486,
          180.0,
          180.0
        ],
        "middle": [
          176.88309636835893,
          172.1164604648962,
          165.86297883928353
        ],
        "ring": [
          174.85741485463325,
          178.38880913670624,
          171.9951848531182
        ],
        "pinky": [
          168.8228884384809,
          172.63057453644595,
          174.6441212621173
        ]
      },
      "wrist_flexion_deg": 3.6517865949623327,
      "confidence": 1.0,
      "timestamp_ms": 2000,
      "active_hand": "left"
    },
    {
      "palm_normal": [
        0.0,
        0.0,
        -1.0
      ],
      "finger_curls": {
        "thumb": [
          166.2838387011987,
          165.96728736463544
        ],
        "index": [
          169.10743559934312,
          170.87025607435737,
          170.47997956788925
        ],
        "middle": [
          179.17409492295704,
          174.6438285737539,
          169.6475920186932
        ],
        "ring": [
          172.41154533501495,
          173.58072644149732,
          157.06203227577876
        ],
        "pinky": [
          166.44623799612475,
          174.6442310243653,
          174.6442310243653
        ]
      },
      "wrist_flexion_deg": 2.825908359649042,
      "confidence": 1.0,
      "timestamp_ms": 2040,
      "active_hand": "left"
    },
    {
      "palm_normal": [
        0.0,
        0.0,
        -1.0
      ],
      "finger_curls": {
        "thumb": [
          168.34556421084807,
          164.14170511449603
        ],
        "index": [
          171.51147300791817,
          170.5393414301664,
          163.32214429278724
        ],
        "middle": [
          179.27206946855088,
          162.88438719956957,
          161.78045669805746
        ],
        "ring": [
          171.09101884433878,
          152.33749120350294,
          160.99343064358715
        ],
        "pinky": [
          165.2588877105099,
          159.0210946014293,
          172.8351361506768
        ]
      },
      "wrist_flexion_deg": 2.382855938250927,
      "confidence": 1.0,
      "timestamp_ms": 2080,
      "active_hand": "left"
    },
    {
      "palm_normal": [
        0.0,
        0.0,
        -1.0
      ],
      "finger_curls": {
        "thumb": [
          162.47347508453245,
          165.1366847196327
        ],
        "index": [
          173.9303985847037,
          175.6927923444322,
          173.42111607817037
        ],
        "middle": [
          177.41714385350988,
          169.83482402324537,
          164.1958976364269
        ],
        "ring": [
          168.06222219087292,
          166.70630830139504,
          139.30084571576307
        ],
        "pinky": [
          161.4188499566481,
          163.99900754069947,
          154.50723336241424
        ]
      },
      "wrist_flexion_deg": 2.1670857488535904,
      "confidence": 1.0,
      "timestamp_ms": 2120,
      "active_hand": "left"
    },
    {
      "palm_normal": [
        0.0,
        0.0,
        -1.0
      ],
      "finger_curls": {
        "thumb": [
          163.70438461259565,
          162.0147860959286
        ],
        "index": [
          172.17398565577585,
          164.4169317195677,
          139.30009156839228
        ],
        "middle": [
          175.9826310924948,
          161.94911556573098,
          112.87380663880091
        ],
        "ring": [
          167.91224845822094,
          148.79899168214112,
          77.0249351657273
        ],
        "pinky": [
          161.18798534427984,
          158.03815840924406,
          150.00849606523803
        ]
      },
      "wrist_flexion_deg": 2.428257581176788,
      "confidence": 1.0,
      "timestamp_ms": 2160,
      "active_hand": "left"
    },
    {
      "palm_normal": [
        0.0,
        0.0,
        -1.0
      ],
      "finger_curls": {
        "thumb": [
          170.52254774482208,
          162.2673595988454
        ],
        "index": [
          175.49702189563124,
          175.9454149567116,
          176.44923182132538
        ],
        "middle": [
          177.37885388851674,
          159.16088115134428,
          174.86969774522885
        ],
        "ring": [
          167.71601492911915,
          145.86447826545933,
          130.15607541094437
        ],
        "pinky": [
          161.98426269250126,
          139.02997875516314,
          138.36611841703868
        ]
      },
      "wrist_flexion_deg": 1.9348210553965157,
      "confidence": 1.0,
      "timestamp_ms": 2200,
      "active_hand": "left"
    },
    {
      "palm_normal": [
        0.0,
        0.0,
        -1.0
      ],
      "finger_curls": {
        "thumb": [
          161.46211138019396,
          167.44901165149165
        ],
        "index": [
          170.8803559785653,
          170.5390297828171,
          176.97159202020933
        ],
        "middle": [
          176.5769744569367,
          155.71765239820314,
          169.201505892884
        ],
        "ring": [
          171.03191536721084,
          148.9099860189861,
          149.07453120517306
        ],
        "pinky": [
          161.42450961192063,
          158.0377383623537,
          143.32142786694254
        ]
      },
      "wrist_flexion_deg": 2.109421379418191,
      "confidence": 1.0,
      "timestamp_ms": 2240,
      "active_hand": "left"
    },
    {
      "palm_normal": [
        0.0,
        0.0,
        -1.0
      ],
      "finger_curls": {
        "thumb": [
          161.4623476968116,
          166.3166148238619
        ],
        "index": [
          171.56089490623805,
          167.86779127002765,
          166.35061137829683
        ],
        "middle": [
          176.2551890221779,
          136.9891697912864,
          169.01799684801438
        ],
        "ring": [
          168.63546998891164,
          143.26569188193048,
          133.15291847305224
        ],
        "pinky": [
          161.65620458645805,
          147.84900592437785,
          130.15585646365102
        ]
      },
      "wrist_flexion_deg": 2.071409869417562,
      "confidence": 1.0,
      "timestamp_ms": 2280,
      "active_hand": "left"
    },
    {
      "palm_normal": [
        0.0,
        0.0,
        -1.0
      ],
      "finger_curls": {
        "thumb": [
          162.2234698718715,
          165.19579164701997
        ],
        "index": [
          173.59344595351254,
          155.717403263993,
          119.35805833315139
        ],
        "middle": [
          177.18686611760006,
          119.318855327065,
          114.4032147584969
        ],
        "ring": [
          168.89405939753846,
          120.83528519765562,
          125.38666817818122
        ],
        "pinky": [
          162.2428651650369,
          128.65617073861506,
          88.70656895888636
        ]
      },
      "wrist_flexion_deg": 2.542682017614448,
      "confidence": 1.0,
      "timestamp_ms": 2320,
      "active_hand": "left"
    },
    {
      "palm_normal": [
        0.0,
        0.0,
        -1.0
      ],
      "finger_curls": {
        "thumb": [
          162.09330274524783,
          164.62361810891065
        ],
        "index": [
          170.70814980585922,
          154.0303301134968,
          58.715831388572795
        ],
        "middle": [
          179.0351050457994,
          93.57630450121727,
          138.36538849065056
        ],
        "ring": [
          171.24388357152108,
          118.25118906672009,
          106.19373372393926
        ],
        "pinky": [
          164.73997563804582,
          125.59512044940695,
          88.70844250822657
        ]
      },
      "wrist_flexion_deg": 2.6113451410385213,
      "confidence": 1.0,
      "timestamp_ms": 2360,
      "active_hand": "left"
    },
    {
      "palm_normal": [
        0.0,
        0.0,
        -1.0
      ],
      "finger_curls": {
        "thumb": [
          159.81931311046324,
          165.14731259259986
        ],
        "index": [
          173.34029501185861,
          155.99789706921686,
          160.9910294603944
        ],
        "middle": [
          176.8088609241906,
          115.2418297393075,
          118.79387016845436
        ],
        "ring": [
          168.89418350372517,
          116.44649803726612,
          129.77509555594418
        ],
        "pinky": [
          162.39765404205392,
          148.5654990254308,
          69.51471041463819
        ]
      },
      "wrist_flexion_deg": 2.4775708924561104,
      "confidence": 1.0,
      "timestamp_ms": 2400,
      "active_hand": "left"
    },
    {
      "palm_normal": [
        0.0,
        0.0,
        -1.0
      ],
      "finger_curls": {
        "thumb": [
          165.379532108211,
          167.56990195029235
        ],
        "index": [
          175.12829865231672,
          163.14758264194808,
          154.50729684050347
        ],
        "middle": [
          175.5903781592436,
          119.98310983367931,
          114.40359164705761
        ],
        "ring": [
          171.28104512771503,
          94.59414416244348,
          138.3660361712889
        ],
        "pinky": [
          165.51630722480303,
          126.48985392451928,
          88.70696659852631
        ]
      },
      "wrist_flexion_deg": 1.8396239987881786,
      "confidence": 1.0,
      "timestamp_ms": 2440,
      "active_hand": "left"
    },
    {
      "palm_normal": [
        0.0,
        0.0,
        -1.0
      ],
      "finger_curls": {
        "thumb": [
          161.2959695011699,
          169.8388690648593
        ],
        "index": [
          174.73612064402408,
          155.99852674973906,
          180.0
        ],
        "middle": [
          176.3399654693383,
          119.31774296041682,
          125.3880924339517
        ],
        "ring": [
          166.39361619398213,
          122.49396851085869,
          125.38605659371542
        ],
        "pinky": [
          164.40804796979546,
          137.47273479967026,
          77.724801869203
        ]
      },
      "wrist_flexion_deg": 2.1561301318213286,
      "confidence": 1.0,
      "timestamp_ms": 2480,
      "active_hand": "left"
    },
    {
      "palm_normal": [
        0.0,
        0.0,
        -1.0
      ],
      "finger_curls": {
        "thumb": [
          168.8088380835627,
          167.44855591210285
        ],
        "index": [
          170.61020408632592,
          152.43192834850998,
          166.35007592551068
        ],
        "middle": [
          177.86613317449888,
          117.74933673033041,
          95.39680423819249
        ],
        "ring": [
          168.0514954013822,
          120.83625566610017,
          95.3924975113538
        ],
        "pinky": [
          163.54088632311834,
          126.49108155708704,
          88.70662030510915
        ]
      },
      "wrist_flexion_deg": 2.3427632555824087,
      "confidence": 1.0,
      "timestamp_ms": 2520,
      "active_hand": "left"
    },
    {
      "palm_normal": [
        0.0,
        0.0,
        -1.0
      ],
      "finger_curls": {
        "thumb": [
          166.53682411215306,
          164.79988054113613
        ],
        "index": [
          172.8422587423532,
          168.3121382009712,
          166.35239154515108
        ],
        "middle": [
          176.02694150490876,
          95.66883377366862,
          119.35780952064927
        ],
        "ring": [
          168.0514294197498,
          96.87312243875952,
          119.3581347402622
        ],
        "pinky": [
          160.65851150949672,
          129.3729273333499,
          88.70624134647579
        ]
      },
      "wrist_flexion_deg": 2.6230869899113722,
      "confidence": 1.0,
      "timestamp_ms": 2560,
      "active_hand": "left"
    },
    {
      "palm_normal": [
        0.0,
        0.0,
        -1.0
      ],
      "finger_curls": {
        "thumb": [
          172.89134974987283,
          162.34539752754952
        ],
        "index": [
          173.44721953211507,
          154.42790577106518,
          58.7172300206339
        ],
        "middle": [
          173.28673821146458,
          97.5395820037191,
          100.62005204574575
        ],
        "ring": [
          165.1046595766343,
          99.13018363974172,
          119.35852461333543
        ],
        "pinky": [
          160.09859530899732,
          122.68388376007492,
          95.39477264619525
        ]
      },
      "wrist_flexion_deg": 2.2273015131917986,
      "confidence": 1.0,
      "timestamp_ms": 2600,
      "active_hand": "left"
    },
    {
      "palm_normal": [
        0.0,
        0.0,
        -1.0
      ],
      "finger_curls": {
        "thumb": [
          170.71422207614503,
          165.14712607462627
        ],
        "index": [
          173.71365699370884,
          168.07700771789854,
          105.70909538044096
        ],
        "middle": [
          175.15750028527813,
          126.31933382503038,
          75.05857993852636
        ],
        "ring": [
          169.79501984278664,
          94.28914736548607,
          138.366447401366
        ],
        "pinky": [
          162.84319432245985,
          145.200211532336,
          80.31183310139448
        ]
      },
      "wrist_flexion_deg": 2.4258382341732316,
      "confidence": 1.0,
      "timestamp_ms": 2640,
      "active_hand": "left"
    },
    {
      "palm_normal": [
        0.0,
        0.0,
        -1.0
      ],
      "finger_curls": {
        "thumb": [
          173.51595915402297,
          162.0721002101823
        ],
        "index": [
          172.7652428967062,
          152.65658269674276,
          58.71460856754459
        ],
        "middle": [
          177.04024329887278,
          69.82320168902734,
          124.58272102445923
        ],
        "ring": [
          169.48992327202313,
          94.59426536082664,
          119.35777425593436
        ],
        "pinky": [
          162.67868482604635,
          126.48996436817527,
          99.50537973857219
        ]
      },
      "wrist_flexion_deg": 2.4372686036835653,
      "confidence": 1.0,
      "timestamp_ms": 2680,
      "active_hand": "left"
    },
    {
      "palm_normal": [
        0.0,
        0.0,
        -1.0
      ],
      "finger_curls": {
        "thumb": [
          168.80862693293963,
          164.39011758037014
        ],
        "index": [
          172.5196593526804,
          133.64641707331552,
          77.72344318511229
        ],
        "middle": [
          177.06195052744343,
          63.13535118951941,
          131.27121534394576
        ],
        "ring": [
          169.33118300383367,
          94.59431846542503,
          119.35734128459649
        ],
        "pinky": [
          161.1196788778162,
          145.68370427671744,
          80.31167546640283
        ]
      },
      "wrist_flexion_deg": 2.4476062857472405,
      "confidence": 1.0,
      "timestamp_ms": 2720,
      "active_hand": "left"
    },
    {
      "palm_normal": [
        0.0,
        0.0,
        -1.0
      ],
      "finger_curls": {
        "thumb": [
          166.53682411215306,
          166.84019241498743
        ],
        "index": [
          173.44727938414604,
          135.4197075879503,
          77.72334881965462
        ],
        "middle": [
          175.17931412718434,
          95.66886508955955,
          105.70839650407545
        ],
        "ring": [
          167.50678670818746,
          96.41878052562797,
          149.35005631292714
        ],
        "pinky": [
          162.84337955656062,
          119.31819338911245,
          114.40298412575329
        ]
      },
      "wrist_flexion_deg": 2.219202474080362,
      "confidence": 1.0,
      "timestamp_ms": 2760,
      "active_hand": "left"
    },
    {
      "palm_normal": [
        0.0,
        0.0,
        -1.0
      ],
      "finger_curls": {
        "thumb": [
          164.38008177809905,
          166.8400874130403
        ],
        "index": [
          172.3970253589123,
          93.57652990955843,
          105.70808963779938
        ],
        "middle": [
          176.29635674467266,
          64.704894234328,
          131.2708563853181
        ],
        "ring": [
          170.63525117862915,
          118.25143137376799,
          95.39547156795928
        ],
        "pinky": [
          163.16226666688223,
          136.98991075359385,
          96.73210952813206
        ]
      },
      "wrist_flexion_deg": 3.0533219593819547,
      "confidence": 1.0,
      "timestamp_ms": 2800,
      "active_hand": "left"
    }
  ],
  "tolerance": {
    "palm_normal_deg": 12.0,
    "wrist_flexion_deg": 8.0,
    "finger_curl_deg": 32.5140789255315
  },
  "default_exemplar_id": "MVI_4577",
  "variant_count": 15
}